exact_kmeans/__init__.py
exact_kmeans/__main__.py
exact_kmeans/callbacks.py
exact_kmeans/config/default.yaml
exact_kmeans/dynamic_program/__init__.py
exact_kmeans/dynamic_program/dp_plain.py
exact_kmeans/ilp.py
exact_kmeans/plot_tree.py
exact_kmeans/util.py
exact_kmeans-0.1.2.dist-info/LICENSE
exact_kmeans-0.1.2.dist-info/WHEEL
exact_kmeans-0.1.2.dist-info/METADATA
exact_kmeans-0.1.2.dist-info/RECORD
