Metadata-Version: 2.1
Name: exact-kmeans
Version: 0.1.2
Summary: Computes an optimal k-means solution for small instances and small k.
License: LICENSE
Author: Melanie Schmidt
Author-email: mschmidt@hhu.de
Requires-Python: >=3.8.1,<4.0.0
Classifier: License :: Other/Proprietary License
Classifier: Programming Language :: Python :: 3
Classifier: Programming Language :: Python :: 3.9
Classifier: Programming Language :: Python :: 3.10
Classifier: Programming Language :: Python :: 3.11
Requires-Dist: gurobipy (>=11.0.3,<12.0.0) ; python_version >= "3.9"
Requires-Dist: gurobipy (>=9.5.1,<10.0.0) ; python_version < "3.9"
Requires-Dist: numpy (>=1.24.4,<2.0.0) ; python_version < "3.12"
Requires-Dist: numpy (>=1.26.4,<2.0.0) ; python_version >= "3.12"
Requires-Dist: pandas (>=2.0.3,<3.0.0)
Requires-Dist: pyyaml (>=6.0.1,<7.0.0)
Requires-Dist: scikit-learn (>=1.3.2,<2.0.0) ; python_version < "3.12"
Requires-Dist: scikit-learn (>=1.4.2,<2.0.0) ; python_version >= "3.12"
Requires-Dist: tqdm (>=4.66.4,<5.0.0)
